{"url":"https://www.greenbelt.org.uk/artists/thomas-trilby/","slug":"thomas-trilby","name":"Thomas Trilby","image":"https://s3-us-west-2.amazonaws.com/marcato.west/artists_files/web_photos/691452/original.jpg","twitter":"https://twitter.com/ThomasTrilby","shows":[{"title":"Thomas Trilby’s Family Show","details":{"location":"Ta Dah!","day":"Monday","time":"15:00"},"desc":"Thomas Trilby has performed from Cardiff to Cairo and Birmingham to Bethlehem. A regular at Glastonbury, Greenbelt and many other festivals, his family show is a fast-moving mixture of circus skills, comedy, audience participation and very silly jokes &#x2013; with something for all ages."}]}